gang/__init__.py
gang-0.0.8.dist-info/DESCRIPTION.rst
gang-0.0.8.dist-info/METADATA
gang-0.0.8.dist-info/WHEEL
gang-0.0.8.dist-info/top_level.txt
gang-0.0.8.dist-info/metadata.json
gang-0.0.8.dist-info/RECORD
